lingpatlab/__init__.py
lingpatlab/analyze/__init__.py
lingpatlab/analyze/bp/__init__.py
lingpatlab/analyze/bp/extract_people.py
lingpatlab/analyze/bp/extract_topics.py
lingpatlab/analyze/dmo/__init__.py
lingpatlab/analyze/dmo/people_sequence_analysis.py
lingpatlab/analyze/dmo/people_sequence_extractor.py
lingpatlab/analyze/dmo/topic_sequence_extractor.py
lingpatlab/analyze/dto/__init__.py
lingpatlab/analyze/dto/text_summary_prompts_1.py
lingpatlab/analyze/dto/text_summary_prompts_2.py
lingpatlab/analyze/svc/__init__.py
lingpatlab/analyze/svc/extract_person_entities.py
lingpatlab/analyze/svc/extract_topic_entities.py
lingpatlab/baseblock/__init__.py
lingpatlab/baseblock/base_object.py
lingpatlab/baseblock/enforce_type.py
lingpatlab/baseblock/env_io.py
lingpatlab/baseblock/file_io.py
lingpatlab/baseblock/stopwatch.py
lingpatlab/lingpatlab.py
lingpatlab/parser/__init__.py
lingpatlab/parser/dmo/__init__.py
lingpatlab/parser/dmo/token_parser_coordinates.py
lingpatlab/parser/dmo/token_parser_normalize.py
lingpatlab/parser/dmo/token_parser_postprocess.py
lingpatlab/parser/dmo/token_parser_punctuation.py
lingpatlab/parser/dmo/token_parser_resultset.py
lingpatlab/parser/dmo/token_parser_spacy.py
lingpatlab/parser/dmo/token_parser_squots.py
lingpatlab/parser/dmo/token_parser_wordnet.py
lingpatlab/parser/dto/__init__.py
lingpatlab/parser/svc/__init__.py
lingpatlab/parser/svc/parse_input_tokens.py
lingpatlab/segmenter/__init__.py
lingpatlab/segmenter/bp/__init__.py
lingpatlab/segmenter/bp/segmenter.py
lingpatlab/segmenter/dmo/__init__.py
lingpatlab/segmenter/dmo/bullet_point_cleaner.py
lingpatlab/segmenter/dmo/delimiters_to_periods.py
lingpatlab/segmenter/dmo/newlines_to_periods.py
lingpatlab/segmenter/dmo/numbered_list_normalizer.py
lingpatlab/segmenter/dmo/post_process_sentences.py
lingpatlab/segmenter/dmo/spacy_doc_segmenter.py
lingpatlab/segmenter/svc/__init__.py
lingpatlab/segmenter/svc/perform_paragraph_segmentation.py
lingpatlab-0.2.13.dist-info/METADATA
lingpatlab-0.2.13.dist-info/WHEEL
lingpatlab-0.2.13.dist-info/RECORD
