Metadata-Version: 2.1
Name: lingpatlab
Version: 0.2.13
Summary: Linguistic Pattern Lab using spaCy
Home-page: https://github.com/craigtrim/lingpatlab
License: MIT
Keywords: nlp,spacy,text-analysis,linguistic-patterns,natural-language-processing,machine-learning,api,cloud,AWS,microservice,utility
Author: Craig Trim
Author-email: craigtrim@gmail.com
Maintainer: Craig Trim
Maintainer-email: craigtrim@gmail.com
Requires-Python: >=3.10,<4.0
Classifier: Development Status :: 4 - Beta
Classifier: Environment :: Web Environment
Classifier: Intended Audience :: Developers
Classifier: License :: OSI Approved :: MIT License
Classifier: Natural Language :: English
Classifier: Operating System :: OS Independent
Classifier: Programming Language :: Python
Classifier: Programming Language :: Python :: 3
Classifier: Programming Language :: Python :: 3.10
Classifier: Programming Language :: Python :: 3.11
Classifier: Programming Language :: Python :: 3.12
Classifier: Programming Language :: Python :: 3.13
Classifier: Topic :: Scientific/Engineering :: Artificial Intelligence
Classifier: Topic :: Software Development :: Libraries :: Python Modules
Classifier: Topic :: Text Processing :: Linguistic
Provides-Extra: linting
Provides-Extra: packaging
Provides-Extra: testing
Requires-Dist: spacy (==3.8.2)
Requires-Dist: unicodedata2
Project-URL: Bug Tracker, https://github.com/craigtrim/lingpatlab/issues
Project-URL: Repository, https://github.com/craigtrim/lingpatlab
